inscribe/__init__.py
inscribe/_version.py
inscribe/config.py
inscribe/errors.py
inscribe-3.1.0.dist-info/METADATA
inscribe-3.1.0.dist-info/WHEEL
inscribe-3.1.0.dist-info/top_level.txt
inscribe-3.1.0.dist-info/RECORD
