Metadata-Version: 2.1
Name: inscribe
Version: 3.1.0
Summary: UNKNOWN
Home-page: https://docs.inscribe.ai
Maintainer: inscribe.ai
Maintainer-email: team@inscribe.ai
License: GPL
Platform: UNKNOWN
Classifier: Development Status :: 4 - Beta
Classifier: Environment :: Console
Classifier: Intended Audience :: Developers
Classifier: Operating System :: OS Independent
Classifier: Programming Language :: Python :: 3
Classifier: Programming Language :: Python :: 3.5
Classifier: Programming Language :: Python :: 3.6
Classifier: Programming Language :: Python :: 3.7
Requires-Dist: requests (>=2.26.0)
